aiojobs/__init__.py
aiojobs/_job.py
aiojobs/_scheduler.py
aiojobs/aiohttp.py
aiojobs/py.typed
aiojobs_fork-1.1.0.dist-info/LICENSE
aiojobs_fork-1.1.0.dist-info/WHEEL
aiojobs_fork-1.1.0.dist-info/METADATA
aiojobs_fork-1.1.0.dist-info/RECORD
